envoy/github/release/__init__.py
envoy/github/release/assets.py
envoy/github/release/manager.py
envoy/github/release/py.typed
envoy/github/release/release.py
envoy/github/release/stream/__init__.py
envoy/github/release/stream/_reader.py
envoy/github/release/stream/_writer.py
envoy/github/release/stream/base.py
envoy.github.release-0.0.15.dist-info/METADATA
envoy.github.release-0.0.15.dist-info/WHEEL
envoy.github.release-0.0.15.dist-info/namespace_packages.txt
envoy.github.release-0.0.15.dist-info/top_level.txt
envoy.github.release-0.0.15.dist-info/RECORD
