Metadata-Version: 2.1
Name: envoy.github.release
Version: 0.0.15
Summary: "Github release tool used in Envoy proxy's CI"
Home-page: https://github.com/envoyproxy/pytooling/tree/main/envoy.github.release
Author: Ryan Northey
Author-email: ryan@synca.io
Maintainer: Ryan Northey
Maintainer-email: ryan@synca.io
License: Apache Software License 2.0
Platform: UNKNOWN
Requires-Dist: abstracts (>=0.0.12)
Requires-Dist: aio.core (>=0.9.1)
Requires-Dist: aio.run.runner (>=0.3.3)
Requires-Dist: aiofiles
Requires-Dist: aiohttp (>=3.8.1)
Requires-Dist: envoy.base.utils (>=0.3.9)
Requires-Dist: envoy.github.abstract (>=0.0.21)
Requires-Dist: gidgethub
Requires-Dist: packaging (>=23.0)
Requires-Dist: verboselogs
